grape/__init__.py
grape/algorithms.py
grape/example_classification.py
grape/example_increment.py
grape/example_parity.py
grape/example_regression.py
grape/functions.py
grape/grape.py
grape/GP/__init__.py
grape/datasets/__init__.py
grape/grammars/__init__.py
grape_bds-0.1.3.dist-info/licenses/LICENSE
grape_bds-0.1.3.dist-info/METADATA
grape_bds-0.1.3.dist-info/WHEEL
grape_bds-0.1.3.dist-info/top_level.txt
grape_bds-0.1.3.dist-info/RECORD
